ResSimpy/DataModelBaseClasses/Aquifer.py
ResSimpy/DataModelBaseClasses/Completion.py
ResSimpy/DataModelBaseClasses/Constraint.py
ResSimpy/DataModelBaseClasses/DataObjectMixin.py
ResSimpy/DataModelBaseClasses/Drill.py
ResSimpy/DataModelBaseClasses/DrillSite.py
ResSimpy/DataModelBaseClasses/DynamicProperty.py
ResSimpy/DataModelBaseClasses/DynamicPropertyContainer.py
ResSimpy/DataModelBaseClasses/Equilibration.py
ResSimpy/DataModelBaseClasses/Ftrans.py
ResSimpy/DataModelBaseClasses/Gaslift.py
ResSimpy/DataModelBaseClasses/Grid.py
ResSimpy/DataModelBaseClasses/GridArrayDefinition.py
ResSimpy/DataModelBaseClasses/GridArrayFunction.py
ResSimpy/DataModelBaseClasses/GuideRate.py
ResSimpy/DataModelBaseClasses/LGR.py
ResSimpy/DataModelBaseClasses/Multir.py
ResSimpy/DataModelBaseClasses/Network.py
ResSimpy/DataModelBaseClasses/NetworkList.py
ResSimpy/DataModelBaseClasses/NetworkObject.py
ResSimpy/DataModelBaseClasses/Node.py
ResSimpy/DataModelBaseClasses/NodeConnection.py
ResSimpy/DataModelBaseClasses/OperationsMixin.py
ResSimpy/DataModelBaseClasses/Over.py
ResSimpy/DataModelBaseClasses/PVT.py
ResSimpy/DataModelBaseClasses/RelPerm.py
ResSimpy/DataModelBaseClasses/RelPermEndPoint.py
ResSimpy/DataModelBaseClasses/Reporting.py
ResSimpy/DataModelBaseClasses/Rock.py
ResSimpy/DataModelBaseClasses/Separator.py
ResSimpy/DataModelBaseClasses/Simulator.py
ResSimpy/DataModelBaseClasses/SolverParameter.py
ResSimpy/DataModelBaseClasses/Target.py
ResSimpy/DataModelBaseClasses/Valve.py
ResSimpy/DataModelBaseClasses/Water.py
ResSimpy/DataModelBaseClasses/Well.py
ResSimpy/DataModelBaseClasses/WellConnection.py
ResSimpy/DataModelBaseClasses/Wellbore.py
ResSimpy/DataModelBaseClasses/Wellhead.py
ResSimpy/DataModelBaseClasses/__init__.py
ResSimpy/DataModelBaseClasses/output_request.py
ResSimpy/Enums/FluidTypeEnums.py
ResSimpy/Enums/FrequencyEnum.py
ResSimpy/Enums/GridFunctionTypes.py
ResSimpy/Enums/HowEnum.py
ResSimpy/Enums/OutputType.py
ResSimpy/Enums/PenetrationDirectionEnum.py
ressimpy-2.4.11.dist-info/LICENSE.MD
ressimpy-2.4.11.dist-info/METADATA
ressimpy-2.4.11.dist-info/WHEEL
ressimpy-2.4.11.dist-info/RECORD
