Metadata-Version: 2.3
Name: ResSimpy
Version: 2.4.11
Summary: A Python library for working with Reservoir Simulator Models.
License: Apache-2.0
Keywords: ResSimpy,Reservoir Engineering
Author: BP
Requires-Python: >=3.10,<3.13
Classifier: Development Status :: 5 - Production/Stable
Classifier: License :: OSI Approved :: Apache Software License
Classifier: Operating System :: OS Independent
Classifier: Programming Language :: Python :: 3
Classifier: Programming Language :: Python :: 3.10
Classifier: Programming Language :: Python :: 3.11
Classifier: Programming Language :: Python :: 3.12
Classifier: Topic :: Scientific/Engineering
Classifier: Topic :: Scientific/Engineering :: Information Analysis
Classifier: Topic :: System :: Filesystems
Requires-Dist: numpy (>=1.26,<2.0)
Requires-Dist: pandas (>=2.2,<3.0)
Requires-Dist: resqpy (>=5.1.11,<6.0.0)
Requires-Dist: typing-extensions (>=4.12,<5.0)
